[
    {
        "issues_url": "https://api.github.com/repos/KoelnAPI/aedmap/issues{/number}", 
        "deployments_url": "https://api.github.com/repos/KoelnAPI/aedmap/deployments", 
        "stargazers_count": 4, 
        "forks_url": "https://api.github.com/repos/KoelnAPI/aedmap/forks", 
        "mirror_url": null, 
        "subscription_url": "https://api.github.com/repos/KoelnAPI/aedmap/subscription", 
        "notifications_url": "https://api.github.com/repos/KoelnAPI/aedmap/notifications{?since,all,participating}", 
        "collaborators_url": "https://api.github.com/repos/KoelnAPI/aedmap/collaborators{/collaborator}", 
        "updated_at": "2016-03-13T18:48:06Z", 
        "private": false, 
        "pulls_url": "https://api.github.com/repos/KoelnAPI/aedmap/pulls{/number}", 
        "issue_comment_url": "https://api.github.com/repos/KoelnAPI/aedmap/issues/comments{/number}", 
        "labels_url": "https://api.github.com/repos/KoelnAPI/aedmap/labels{/name}", 
        "has_wiki": true, 
        "full_name": "KoelnAPI/aedmap", 
        "owner": {
            "following_url": "https://api.github.com/users/KoelnAPI/following{/other_user}", 
            "events_url": "https://api.github.com/users/KoelnAPI/events{/privacy}", 
            "organizations_url": "https://api.github.com/users/KoelnAPI/orgs", 
            "url": "https://api.github.com/users/KoelnAPI", 
            "gists_url": "https://api.github.com/users/KoelnAPI/gists{/gist_id}", 
            "html_url": "https://github.com/KoelnAPI", 
            "subscriptions_url": "https://api.github.com/users/KoelnAPI/subscriptions", 
            "avatar_url": "https://avatars.githubusercontent.com/u/5716567?v=3", 
            "repos_url": "https://api.github.com/users/KoelnAPI/repos", 
            "received_events_url": "https://api.github.com/users/KoelnAPI/received_events", 
            "gravatar_id": "", 
            "starred_url": "https://api.github.com/users/KoelnAPI/starred{/owner}{/repo}", 
            "site_admin": false, 
            "login": "KoelnAPI", 
            "type": "Organization", 
            "id": 5716567, 
            "followers_url": "https://api.github.com/users/KoelnAPI/followers"
        }, 
        "statuses_url": "https://api.github.com/repos/KoelnAPI/aedmap/statuses/{sha}", 
        "id": 17979625, 
        "keys_url": "https://api.github.com/repos/KoelnAPI/aedmap/keys{/key_id}", 
        "description": "Mobile web application for the display of automated external defibrillator (AED) locations", 
        "tags_url": "https://api.github.com/repos/KoelnAPI/aedmap/tags", 
        "downloads_url": "https://api.github.com/repos/KoelnAPI/aedmap/downloads", 
        "assignees_url": "https://api.github.com/repos/KoelnAPI/aedmap/assignees{/user}", 
        "contents_url": "https://api.github.com/repos/KoelnAPI/aedmap/contents/{+path}", 
        "has_pages": false, 
        "git_refs_url": "https://api.github.com/repos/KoelnAPI/aedmap/git/refs{/sha}", 
        "open_issues_count": 10, 
        "clone_url": "https://github.com/KoelnAPI/aedmap.git", 
        "watchers_count": 4, 
        "git_tags_url": "https://api.github.com/repos/KoelnAPI/aedmap/git/tags{/sha}", 
        "milestones_url": "https://api.github.com/repos/KoelnAPI/aedmap/milestones{/number}", 
        "languages_url": "https://api.github.com/repos/KoelnAPI/aedmap/languages", 
        "size": 1984, 
        "homepage": null, 
        "fork": false, 
        "commits_url": "https://api.github.com/repos/KoelnAPI/aedmap/commits{/sha}", 
        "releases_url": "https://api.github.com/repos/KoelnAPI/aedmap/releases{/id}", 
        "issue_events_url": "https://api.github.com/repos/KoelnAPI/aedmap/issues/events{/number}", 
        "archive_url": "https://api.github.com/repos/KoelnAPI/aedmap/{archive_format}{/ref}", 
        "comments_url": "https://api.github.com/repos/KoelnAPI/aedmap/comments{/number}", 
        "events_url": "https://api.github.com/repos/KoelnAPI/aedmap/events", 
        "contributors_url": "https://api.github.com/repos/KoelnAPI/aedmap/contributors", 
        "html_url": "https://github.com/KoelnAPI/aedmap", 
        "forks": 1, 
        "compare_url": "https://api.github.com/repos/KoelnAPI/aedmap/compare/{base}...{head}", 
        "open_issues": 10, 
        "git_url": "git://github.com/KoelnAPI/aedmap.git", 
        "svn_url": "https://github.com/KoelnAPI/aedmap", 
        "merges_url": "https://api.github.com/repos/KoelnAPI/aedmap/merges", 
        "has_issues": true, 
        "ssh_url": "git@github.com:KoelnAPI/aedmap.git", 
        "blobs_url": "https://api.github.com/repos/KoelnAPI/aedmap/git/blobs{/sha}", 
        "git_commits_url": "https://api.github.com/repos/KoelnAPI/aedmap/git/commits{/sha}", 
        "hooks_url": "https://api.github.com/repos/KoelnAPI/aedmap/hooks", 
        "has_downloads": true, 
        "watchers": 4, 
        "name": "aedmap", 
        "language": "CSS", 
        "url": "https://api.github.com/repos/KoelnAPI/aedmap", 
        "created_at": "2014-03-21T12:45:08Z", 
        "pushed_at": "2014-06-24T09:53:12Z", 
        "forks_count": 1, 
        "default_branch": "master", 
        "teams_url": "https://api.github.com/repos/KoelnAPI/aedmap/teams", 
        "trees_url": "https://api.github.com/repos/KoelnAPI/aedmap/git/trees{/sha}", 
        "branches_url": "https://api.github.com/repos/KoelnAPI/aedmap/branches{/branch}", 
        "subscribers_url": "https://api.github.com/repos/KoelnAPI/aedmap/subscribers", 
        "permissions": {
            "admin": false, 
            "push": false, 
            "pull": true
        }, 
        "stargazers_url": "https://api.github.com/repos/KoelnAPI/aedmap/stargazers"
    }, 
    {
        "issues_url": "https://api.github.com/repos/KoelnAPI/brand/issues{/number}", 
        "deployments_url": "https://api.github.com/repos/KoelnAPI/brand/deployments", 
        "stargazers_count": 0, 
        "forks_url": "https://api.github.com/repos/KoelnAPI/brand/forks", 
        "mirror_url": null, 
        "subscription_url": "https://api.github.com/repos/KoelnAPI/brand/subscription", 
        "notifications_url": "https://api.github.com/repos/KoelnAPI/brand/notifications{?since,all,participating}", 
        "collaborators_url": "https://api.github.com/repos/KoelnAPI/brand/collaborators{/collaborator}", 
        "updated_at": "2014-06-11T11:16:03Z", 
        "private": false, 
        "pulls_url": "https://api.github.com/repos/KoelnAPI/brand/pulls{/number}", 
        "issue_comment_url": "https://api.github.com/repos/KoelnAPI/brand/issues/comments{/number}", 
        "labels_url": "https://api.github.com/repos/KoelnAPI/brand/labels{/name}", 
        "has_wiki": true, 
        "full_name": "KoelnAPI/brand", 
        "owner": {
            "following_url": "https://api.github.com/users/KoelnAPI/following{/other_user}", 
            "events_url": "https://api.github.com/users/KoelnAPI/events{/privacy}", 
            "organizations_url": "https://api.github.com/users/KoelnAPI/orgs", 
            "url": "https://api.github.com/users/KoelnAPI", 
            "gists_url": "https://api.github.com/users/KoelnAPI/gists{/gist_id}", 
            "html_url": "https://github.com/KoelnAPI", 
            "subscriptions_url": "https://api.github.com/users/KoelnAPI/subscriptions", 
            "avatar_url": "https://avatars.githubusercontent.com/u/5716567?v=3", 
            "repos_url": "https://api.github.com/users/KoelnAPI/repos", 
            "received_events_url": "https://api.github.com/users/KoelnAPI/received_events", 
            "gravatar_id": "", 
            "starred_url": "https://api.github.com/users/KoelnAPI/starred{/owner}{/repo}", 
            "site_admin": false, 
            "login": "KoelnAPI", 
            "type": "Organization", 
            "id": 5716567, 
            "followers_url": "https://api.github.com/users/KoelnAPI/followers"
        }, 
        "statuses_url": "https://api.github.com/repos/KoelnAPI/brand/statuses/{sha}", 
        "id": 16022527, 
        "keys_url": "https://api.github.com/repos/KoelnAPI/brand/keys{/key_id}", 
        "description": "Das K\u00f6ln API Logo", 
        "tags_url": "https://api.github.com/repos/KoelnAPI/brand/tags", 
        "downloads_url": "https://api.github.com/repos/KoelnAPI/brand/downloads", 
        "assignees_url": "https://api.github.com/repos/KoelnAPI/brand/assignees{/user}", 
        "contents_url": "https://api.github.com/repos/KoelnAPI/brand/contents/{+path}", 
        "has_pages": false, 
        "git_refs_url": "https://api.github.com/repos/KoelnAPI/brand/git/refs{/sha}", 
        "open_issues_count": 0, 
        "clone_url": "https://github.com/KoelnAPI/brand.git", 
        "watchers_count": 0, 
        "git_tags_url": "https://api.github.com/repos/KoelnAPI/brand/git/tags{/sha}", 
        "milestones_url": "https://api.github.com/repos/KoelnAPI/brand/milestones{/number}", 
        "languages_url": "https://api.github.com/repos/KoelnAPI/brand/languages", 
        "size": 3500, 
        "homepage": null, 
        "fork": false, 
        "commits_url": "https://api.github.com/repos/KoelnAPI/brand/commits{/sha}", 
        "releases_url": "https://api.github.com/repos/KoelnAPI/brand/releases{/id}", 
        "issue_events_url": "https://api.github.com/repos/KoelnAPI/brand/issues/events{/number}", 
        "archive_url": "https://api.github.com/repos/KoelnAPI/brand/{archive_format}{/ref}", 
        "comments_url": "https://api.github.com/repos/KoelnAPI/brand/comments{/number}", 
        "events_url": "https://api.github.com/repos/KoelnAPI/brand/events", 
        "contributors_url": "https://api.github.com/repos/KoelnAPI/brand/contributors", 
        "html_url": "https://github.com/KoelnAPI/brand", 
        "forks": 0, 
        "compare_url": "https://api.github.com/repos/KoelnAPI/brand/compare/{base}...{head}", 
        "open_issues": 0, 
        "git_url": "git://github.com/KoelnAPI/brand.git", 
        "svn_url": "https://github.com/KoelnAPI/brand", 
        "merges_url": "https://api.github.com/repos/KoelnAPI/brand/merges", 
        "has_issues": true, 
        "ssh_url": "git@github.com:KoelnAPI/brand.git", 
        "blobs_url": "https://api.github.com/repos/KoelnAPI/brand/git/blobs{/sha}", 
        "git_commits_url": "https://api.github.com/repos/KoelnAPI/brand/git/commits{/sha}", 
        "hooks_url": "https://api.github.com/repos/KoelnAPI/brand/hooks", 
        "has_downloads": true, 
        "watchers": 0, 
        "name": "brand", 
        "language": null, 
        "url": "https://api.github.com/repos/KoelnAPI/brand", 
        "created_at": "2014-01-18T09:19:28Z", 
        "pushed_at": "2014-06-11T11:16:03Z", 
        "forks_count": 0, 
        "default_branch": "master", 
        "teams_url": "https://api.github.com/repos/KoelnAPI/brand/teams", 
        "trees_url": "https://api.github.com/repos/KoelnAPI/brand/git/trees{/sha}", 
        "branches_url": "https://api.github.com/repos/KoelnAPI/brand/branches{/branch}", 
        "subscribers_url": "https://api.github.com/repos/KoelnAPI/brand/subscribers", 
        "permissions": {
            "admin": false, 
            "push": false, 
            "pull": true
        }, 
        "stargazers_url": "https://api.github.com/repos/KoelnAPI/brand/stargazers"
    }, 
    {
        "issues_url": "https://api.github.com/repos/KoelnAPI/data/issues{/number}", 
        "deployments_url": "https://api.github.com/repos/KoelnAPI/data/deployments", 
        "stargazers_count": 26, 
        "forks_url": "https://api.github.com/repos/KoelnAPI/data/forks", 
        "mirror_url": null, 
        "subscription_url": "https://api.github.com/repos/KoelnAPI/data/subscription", 
        "notifications_url": "https://api.github.com/repos/KoelnAPI/data/notifications{?since,all,participating}", 
        "collaborators_url": "https://api.github.com/repos/KoelnAPI/data/collaborators{/collaborator}", 
        "updated_at": "2016-06-01T08:53:06Z", 
        "private": false, 
        "pulls_url": "https://api.github.com/repos/KoelnAPI/data/pulls{/number}", 
        "issue_comment_url": "https://api.github.com/repos/KoelnAPI/data/issues/comments{/number}", 
        "labels_url": "https://api.github.com/repos/KoelnAPI/data/labels{/name}", 
        "has_wiki": true, 
        "full_name": "KoelnAPI/data", 
        "owner": {
            "following_url": "https://api.github.com/users/KoelnAPI/following{/other_user}", 
            "events_url": "https://api.github.com/users/KoelnAPI/events{/privacy}", 
            "organizations_url": "https://api.github.com/users/KoelnAPI/orgs", 
            "url": "https://api.github.com/users/KoelnAPI", 
            "gists_url": "https://api.github.com/users/KoelnAPI/gists{/gist_id}", 
            "html_url": "https://github.com/KoelnAPI", 
            "subscriptions_url": "https://api.github.com/users/KoelnAPI/subscriptions", 
            "avatar_url": "https://avatars.githubusercontent.com/u/5716567?v=3", 
            "repos_url": "https://api.github.com/users/KoelnAPI/repos", 
            "received_events_url": "https://api.github.com/users/KoelnAPI/received_events", 
            "gravatar_id": "", 
            "starred_url": "https://api.github.com/users/KoelnAPI/starred{/owner}{/repo}", 
            "site_admin": false, 
            "login": "KoelnAPI", 
            "type": "Organization", 
            "id": 5716567, 
            "followers_url": "https://api.github.com/users/KoelnAPI/followers"
        }, 
        "statuses_url": "https://api.github.com/repos/KoelnAPI/data/statuses/{sha}", 
        "id": 10940801, 
        "keys_url": "https://api.github.com/repos/KoelnAPI/data/keys{/key_id}", 
        "description": "Repository f\u00fcr den bequemen Zugang zu einigen Open-Data-Angeboten aus K\u00f6ln", 
        "tags_url": "https://api.github.com/repos/KoelnAPI/data/tags", 
        "downloads_url": "https://api.github.com/repos/KoelnAPI/data/downloads", 
        "assignees_url": "https://api.github.com/repos/KoelnAPI/data/assignees{/user}", 
        "contents_url": "https://api.github.com/repos/KoelnAPI/data/contents/{+path}", 
        "has_pages": false, 
        "git_refs_url": "https://api.github.com/repos/KoelnAPI/data/git/refs{/sha}", 
        "open_issues_count": 4, 
        "clone_url": "https://github.com/KoelnAPI/data.git", 
        "watchers_count": 26, 
        "git_tags_url": "https://api.github.com/repos/KoelnAPI/data/git/tags{/sha}", 
        "milestones_url": "https://api.github.com/repos/KoelnAPI/data/milestones{/number}", 
        "languages_url": "https://api.github.com/repos/KoelnAPI/data/languages", 
        "size": 109916, 
        "homepage": "", 
        "fork": false, 
        "commits_url": "https://api.github.com/repos/KoelnAPI/data/commits{/sha}", 
        "releases_url": "https://api.github.com/repos/KoelnAPI/data/releases{/id}", 
        "issue_events_url": "https://api.github.com/repos/KoelnAPI/data/issues/events{/number}", 
        "archive_url": "https://api.github.com/repos/KoelnAPI/data/{archive_format}{/ref}", 
        "comments_url": "https://api.github.com/repos/KoelnAPI/data/comments{/number}", 
        "events_url": "https://api.github.com/repos/KoelnAPI/data/events", 
        "contributors_url": "https://api.github.com/repos/KoelnAPI/data/contributors", 
        "html_url": "https://github.com/KoelnAPI/data", 
        "forks": 14, 
        "compare_url": "https://api.github.com/repos/KoelnAPI/data/compare/{base}...{head}", 
        "open_issues": 4, 
        "git_url": "git://github.com/KoelnAPI/data.git", 
        "svn_url": "https://github.com/KoelnAPI/data", 
        "merges_url": "https://api.github.com/repos/KoelnAPI/data/merges", 
        "has_issues": true, 
        "ssh_url": "git@github.com:KoelnAPI/data.git", 
        "blobs_url": "https://api.github.com/repos/KoelnAPI/data/git/blobs{/sha}", 
        "git_commits_url": "https://api.github.com/repos/KoelnAPI/data/git/commits{/sha}", 
        "hooks_url": "https://api.github.com/repos/KoelnAPI/data/hooks", 
        "has_downloads": true, 
        "watchers": 26, 
        "name": "data", 
        "language": "Python", 
        "url": "https://api.github.com/repos/KoelnAPI/data", 
        "created_at": "2013-06-25T14:35:48Z", 
        "pushed_at": "2015-11-04T15:24:06Z", 
        "forks_count": 14, 
        "default_branch": "master", 
        "teams_url": "https://api.github.com/repos/KoelnAPI/data/teams", 
        "trees_url": "https://api.github.com/repos/KoelnAPI/data/git/trees{/sha}", 
        "branches_url": "https://api.github.com/repos/KoelnAPI/data/branches{/branch}", 
        "subscribers_url": "https://api.github.com/repos/KoelnAPI/data/subscribers", 
        "permissions": {
            "admin": false, 
            "push": false, 
            "pull": true
        }, 
        "stargazers_url": "https://api.github.com/repos/KoelnAPI/data/stargazers"
    }, 
    {
        "issues_url": "https://api.github.com/repos/KoelnAPI/geoserver/issues{/number}", 
        "deployments_url": "https://api.github.com/repos/KoelnAPI/geoserver/deployments", 
        "stargazers_count": 0, 
        "forks_url": "https://api.github.com/repos/KoelnAPI/geoserver/forks", 
        "mirror_url": null, 
        "subscription_url": "https://api.github.com/repos/KoelnAPI/geoserver/subscription", 
        "notifications_url": "https://api.github.com/repos/KoelnAPI/geoserver/notifications{?since,all,participating}", 
        "collaborators_url": "https://api.github.com/repos/KoelnAPI/geoserver/collaborators{/collaborator}", 
        "updated_at": "2014-04-29T06:55:20Z", 
        "private": false, 
        "pulls_url": "https://api.github.com/repos/KoelnAPI/geoserver/pulls{/number}", 
        "issue_comment_url": "https://api.github.com/repos/KoelnAPI/geoserver/issues/comments{/number}", 
        "labels_url": "https://api.github.com/repos/KoelnAPI/geoserver/labels{/name}", 
        "has_wiki": true, 
        "full_name": "KoelnAPI/geoserver", 
        "owner": {
            "following_url": "https://api.github.com/users/KoelnAPI/following{/other_user}", 
            "events_url": "https://api.github.com/users/KoelnAPI/events{/privacy}", 
            "organizations_url": "https://api.github.com/users/KoelnAPI/orgs", 
            "url": "https://api.github.com/users/KoelnAPI", 
            "gists_url": "https://api.github.com/users/KoelnAPI/gists{/gist_id}", 
            "html_url": "https://github.com/KoelnAPI", 
            "subscriptions_url": "https://api.github.com/users/KoelnAPI/subscriptions", 
            "avatar_url": "https://avatars.githubusercontent.com/u/5716567?v=3", 
            "repos_url": "https://api.github.com/users/KoelnAPI/repos", 
            "received_events_url": "https://api.github.com/users/KoelnAPI/received_events", 
            "gravatar_id": "", 
            "starred_url": "https://api.github.com/users/KoelnAPI/starred{/owner}{/repo}", 
            "site_admin": false, 
            "login": "KoelnAPI", 
            "type": "Organization", 
            "id": 5716567, 
            "followers_url": "https://api.github.com/users/KoelnAPI/followers"
        }, 
        "statuses_url": "https://api.github.com/repos/KoelnAPI/geoserver/statuses/{sha}", 
        "id": 19243621, 
        "keys_url": "https://api.github.com/repos/KoelnAPI/geoserver/keys{/key_id}", 
        "description": "Code repository for a geodata centric PostGIS server, possibly with a visualization layer", 
        "tags_url": "https://api.github.com/repos/KoelnAPI/geoserver/tags", 
        "downloads_url": "https://api.github.com/repos/KoelnAPI/geoserver/downloads", 
        "assignees_url": "https://api.github.com/repos/KoelnAPI/geoserver/assignees{/user}", 
        "contents_url": "https://api.github.com/repos/KoelnAPI/geoserver/contents/{+path}", 
        "has_pages": false, 
        "git_refs_url": "https://api.github.com/repos/KoelnAPI/geoserver/git/refs{/sha}", 
        "open_issues_count": 0, 
        "clone_url": "https://github.com/KoelnAPI/geoserver.git", 
        "watchers_count": 0, 
        "git_tags_url": "https://api.github.com/repos/KoelnAPI/geoserver/git/tags{/sha}", 
        "milestones_url": "https://api.github.com/repos/KoelnAPI/geoserver/milestones{/number}", 
        "languages_url": "https://api.github.com/repos/KoelnAPI/geoserver/languages", 
        "size": 248, 
        "homepage": null, 
        "fork": false, 
        "commits_url": "https://api.github.com/repos/KoelnAPI/geoserver/commits{/sha}", 
        "releases_url": "https://api.github.com/repos/KoelnAPI/geoserver/releases{/id}", 
        "issue_events_url": "https://api.github.com/repos/KoelnAPI/geoserver/issues/events{/number}", 
        "archive_url": "https://api.github.com/repos/KoelnAPI/geoserver/{archive_format}{/ref}", 
        "comments_url": "https://api.github.com/repos/KoelnAPI/geoserver/comments{/number}", 
        "events_url": "https://api.github.com/repos/KoelnAPI/geoserver/events", 
        "contributors_url": "https://api.github.com/repos/KoelnAPI/geoserver/contributors", 
        "html_url": "https://github.com/KoelnAPI/geoserver", 
        "forks": 0, 
        "compare_url": "https://api.github.com/repos/KoelnAPI/geoserver/compare/{base}...{head}", 
        "open_issues": 0, 
        "git_url": "git://github.com/KoelnAPI/geoserver.git", 
        "svn_url": "https://github.com/KoelnAPI/geoserver", 
        "merges_url": "https://api.github.com/repos/KoelnAPI/geoserver/merges", 
        "has_issues": true, 
        "ssh_url": "git@github.com:KoelnAPI/geoserver.git", 
        "blobs_url": "https://api.github.com/repos/KoelnAPI/geoserver/git/blobs{/sha}", 
        "git_commits_url": "https://api.github.com/repos/KoelnAPI/geoserver/git/commits{/sha}", 
        "hooks_url": "https://api.github.com/repos/KoelnAPI/geoserver/hooks", 
        "has_downloads": true, 
        "watchers": 0, 
        "name": "geoserver", 
        "language": "Shell", 
        "url": "https://api.github.com/repos/KoelnAPI/geoserver", 
        "created_at": "2014-04-28T15:28:49Z", 
        "pushed_at": "2014-04-29T06:55:21Z", 
        "forks_count": 0, 
        "default_branch": "master", 
        "teams_url": "https://api.github.com/repos/KoelnAPI/geoserver/teams", 
        "trees_url": "https://api.github.com/repos/KoelnAPI/geoserver/git/trees{/sha}", 
        "branches_url": "https://api.github.com/repos/KoelnAPI/geoserver/branches{/branch}", 
        "subscribers_url": "https://api.github.com/repos/KoelnAPI/geoserver/subscribers", 
        "permissions": {
            "admin": false, 
            "push": false, 
            "pull": true
        }, 
        "stargazers_url": "https://api.github.com/repos/KoelnAPI/geoserver/stargazers"
    }, 
    {
        "issues_url": "https://api.github.com/repos/KoelnAPI/KoelnAPI.github.io/issues{/number}", 
        "deployments_url": "https://api.github.com/repos/KoelnAPI/KoelnAPI.github.io/deployments", 
        "stargazers_count": 0, 
        "forks_url": "https://api.github.com/repos/KoelnAPI/KoelnAPI.github.io/forks", 
        "mirror_url": null, 
        "subscription_url": "https://api.github.com/repos/KoelnAPI/KoelnAPI.github.io/subscription", 
        "notifications_url": "https://api.github.com/repos/KoelnAPI/KoelnAPI.github.io/notifications{?since,all,participating}", 
        "collaborators_url": "https://api.github.com/repos/KoelnAPI/KoelnAPI.github.io/collaborators{/collaborator}", 
        "updated_at": "2016-01-19T11:11:54Z", 
        "private": false, 
        "pulls_url": "https://api.github.com/repos/KoelnAPI/KoelnAPI.github.io/pulls{/number}", 
        "issue_comment_url": "https://api.github.com/repos/KoelnAPI/KoelnAPI.github.io/issues/comments{/number}", 
        "labels_url": "https://api.github.com/repos/KoelnAPI/KoelnAPI.github.io/labels{/name}", 
        "has_wiki": true, 
        "full_name": "KoelnAPI/KoelnAPI.github.io", 
        "owner": {
            "following_url": "https://api.github.com/users/KoelnAPI/following{/other_user}", 
            "events_url": "https://api.github.com/users/KoelnAPI/events{/privacy}", 
            "organizations_url": "https://api.github.com/users/KoelnAPI/orgs", 
            "url": "https://api.github.com/users/KoelnAPI", 
            "gists_url": "https://api.github.com/users/KoelnAPI/gists{/gist_id}", 
            "html_url": "https://github.com/KoelnAPI", 
            "subscriptions_url": "https://api.github.com/users/KoelnAPI/subscriptions", 
            "avatar_url": "https://avatars.githubusercontent.com/u/5716567?v=3", 
            "repos_url": "https://api.github.com/users/KoelnAPI/repos", 
            "received_events_url": "https://api.github.com/users/KoelnAPI/received_events", 
            "gravatar_id": "", 
            "starred_url": "https://api.github.com/users/KoelnAPI/starred{/owner}{/repo}", 
            "site_admin": false, 
            "login": "KoelnAPI", 
            "type": "Organization", 
            "id": 5716567, 
            "followers_url": "https://api.github.com/users/KoelnAPI/followers"
        }, 
        "statuses_url": "https://api.github.com/repos/KoelnAPI/KoelnAPI.github.io/statuses/{sha}", 
        "id": 18190344, 
        "keys_url": "https://api.github.com/repos/KoelnAPI/KoelnAPI.github.io/keys{/key_id}", 
        "description": "Website", 
        "tags_url": "https://api.github.com/repos/KoelnAPI/KoelnAPI.github.io/tags", 
        "downloads_url": "https://api.github.com/repos/KoelnAPI/KoelnAPI.github.io/downloads", 
        "assignees_url": "https://api.github.com/repos/KoelnAPI/KoelnAPI.github.io/assignees{/user}", 
        "contents_url": "https://api.github.com/repos/KoelnAPI/KoelnAPI.github.io/contents/{+path}", 
        "has_pages": true, 
        "git_refs_url": "https://api.github.com/repos/KoelnAPI/KoelnAPI.github.io/git/refs{/sha}", 
        "open_issues_count": 0, 
        "clone_url": "https://github.com/KoelnAPI/KoelnAPI.github.io.git", 
        "watchers_count": 0, 
        "git_tags_url": "https://api.github.com/repos/KoelnAPI/KoelnAPI.github.io/git/tags{/sha}", 
        "milestones_url": "https://api.github.com/repos/KoelnAPI/KoelnAPI.github.io/milestones{/number}", 
        "languages_url": "https://api.github.com/repos/KoelnAPI/KoelnAPI.github.io/languages", 
        "size": 6856, 
        "homepage": null, 
        "fork": false, 
        "commits_url": "https://api.github.com/repos/KoelnAPI/KoelnAPI.github.io/commits{/sha}", 
        "releases_url": "https://api.github.com/repos/KoelnAPI/KoelnAPI.github.io/releases{/id}", 
        "issue_events_url": "https://api.github.com/repos/KoelnAPI/KoelnAPI.github.io/issues/events{/number}", 
        "archive_url": "https://api.github.com/repos/KoelnAPI/KoelnAPI.github.io/{archive_format}{/ref}", 
        "comments_url": "https://api.github.com/repos/KoelnAPI/KoelnAPI.github.io/comments{/number}", 
        "events_url": "https://api.github.com/repos/KoelnAPI/KoelnAPI.github.io/events", 
        "contributors_url": "https://api.github.com/repos/KoelnAPI/KoelnAPI.github.io/contributors", 
        "html_url": "https://github.com/KoelnAPI/KoelnAPI.github.io", 
        "forks": 1, 
        "compare_url": "https://api.github.com/repos/KoelnAPI/KoelnAPI.github.io/compare/{base}...{head}", 
        "open_issues": 0, 
        "git_url": "git://github.com/KoelnAPI/KoelnAPI.github.io.git", 
        "svn_url": "https://github.com/KoelnAPI/KoelnAPI.github.io", 
        "merges_url": "https://api.github.com/repos/KoelnAPI/KoelnAPI.github.io/merges", 
        "has_issues": true, 
        "ssh_url": "git@github.com:KoelnAPI/KoelnAPI.github.io.git", 
        "blobs_url": "https://api.github.com/repos/KoelnAPI/KoelnAPI.github.io/git/blobs{/sha}", 
        "git_commits_url": "https://api.github.com/repos/KoelnAPI/KoelnAPI.github.io/git/commits{/sha}", 
        "hooks_url": "https://api.github.com/repos/KoelnAPI/KoelnAPI.github.io/hooks", 
        "has_downloads": true, 
        "watchers": 0, 
        "name": "KoelnAPI.github.io", 
        "language": "HTML", 
        "url": "https://api.github.com/repos/KoelnAPI/KoelnAPI.github.io", 
        "created_at": "2014-03-27T20:29:24Z", 
        "pushed_at": "2016-09-05T19:48:21Z", 
        "forks_count": 1, 
        "default_branch": "master", 
        "teams_url": "https://api.github.com/repos/KoelnAPI/KoelnAPI.github.io/teams", 
        "trees_url": "https://api.github.com/repos/KoelnAPI/KoelnAPI.github.io/git/trees{/sha}", 
        "branches_url": "https://api.github.com/repos/KoelnAPI/KoelnAPI.github.io/branches{/branch}", 
        "subscribers_url": "https://api.github.com/repos/KoelnAPI/KoelnAPI.github.io/subscribers", 
        "permissions": {
            "admin": false, 
            "push": false, 
            "pull": true
        }, 
        "stargazers_url": "https://api.github.com/repos/KoelnAPI/KoelnAPI.github.io/stargazers"
    }, 
    {
        "issues_url": "https://api.github.com/repos/KoelnAPI/kvb-api/issues{/number}", 
        "deployments_url": "https://api.github.com/repos/KoelnAPI/kvb-api/deployments", 
        "stargazers_count": 0, 
        "forks_url": "https://api.github.com/repos/KoelnAPI/kvb-api/forks", 
        "mirror_url": null, 
        "subscription_url": "https://api.github.com/repos/KoelnAPI/kvb-api/subscription", 
        "notifications_url": "https://api.github.com/repos/KoelnAPI/kvb-api/notifications{?since,all,participating}", 
        "collaborators_url": "https://api.github.com/repos/KoelnAPI/kvb-api/collaborators{/collaborator}", 
        "updated_at": "2015-11-27T15:51:56Z", 
        "private": false, 
        "pulls_url": "https://api.github.com/repos/KoelnAPI/kvb-api/pulls{/number}", 
        "issue_comment_url": "https://api.github.com/repos/KoelnAPI/kvb-api/issues/comments{/number}", 
        "labels_url": "https://api.github.com/repos/KoelnAPI/kvb-api/labels{/name}", 
        "has_wiki": true, 
        "full_name": "KoelnAPI/kvb-api", 
        "owner": {
            "following_url": "https://api.github.com/users/KoelnAPI/following{/other_user}", 
            "events_url": "https://api.github.com/users/KoelnAPI/events{/privacy}", 
            "organizations_url": "https://api.github.com/users/KoelnAPI/orgs", 
            "url": "https://api.github.com/users/KoelnAPI", 
            "gists_url": "https://api.github.com/users/KoelnAPI/gists{/gist_id}", 
            "html_url": "https://github.com/KoelnAPI", 
            "subscriptions_url": "https://api.github.com/users/KoelnAPI/subscriptions", 
            "avatar_url": "https://avatars.githubusercontent.com/u/5716567?v=3", 
            "repos_url": "https://api.github.com/users/KoelnAPI/repos", 
            "received_events_url": "https://api.github.com/users/KoelnAPI/received_events", 
            "gravatar_id": "", 
            "starred_url": "https://api.github.com/users/KoelnAPI/starred{/owner}{/repo}", 
            "site_admin": false, 
            "login": "KoelnAPI", 
            "type": "Organization", 
            "id": 5716567, 
            "followers_url": "https://api.github.com/users/KoelnAPI/followers"
        }, 
        "statuses_url": "https://api.github.com/repos/KoelnAPI/kvb-api/statuses/{sha}", 
        "id": 20330304, 
        "keys_url": "https://api.github.com/repos/KoelnAPI/kvb-api/keys{/key_id}", 
        "description": "", 
        "tags_url": "https://api.github.com/repos/KoelnAPI/kvb-api/tags", 
        "downloads_url": "https://api.github.com/repos/KoelnAPI/kvb-api/downloads", 
        "assignees_url": "https://api.github.com/repos/KoelnAPI/kvb-api/assignees{/user}", 
        "contents_url": "https://api.github.com/repos/KoelnAPI/kvb-api/contents/{+path}", 
        "has_pages": false, 
        "git_refs_url": "https://api.github.com/repos/KoelnAPI/kvb-api/git/refs{/sha}", 
        "open_issues_count": 0, 
        "clone_url": "https://github.com/KoelnAPI/kvb-api.git", 
        "watchers_count": 0, 
        "git_tags_url": "https://api.github.com/repos/KoelnAPI/kvb-api/git/tags{/sha}", 
        "milestones_url": "https://api.github.com/repos/KoelnAPI/kvb-api/milestones{/number}", 
        "languages_url": "https://api.github.com/repos/KoelnAPI/kvb-api/languages", 
        "size": 5, 
        "homepage": null, 
        "fork": false, 
        "commits_url": "https://api.github.com/repos/KoelnAPI/kvb-api/commits{/sha}", 
        "releases_url": "https://api.github.com/repos/KoelnAPI/kvb-api/releases{/id}", 
        "issue_events_url": "https://api.github.com/repos/KoelnAPI/kvb-api/issues/events{/number}", 
        "archive_url": "https://api.github.com/repos/KoelnAPI/kvb-api/{archive_format}{/ref}", 
        "comments_url": "https://api.github.com/repos/KoelnAPI/kvb-api/comments{/number}", 
        "events_url": "https://api.github.com/repos/KoelnAPI/kvb-api/events", 
        "contributors_url": "https://api.github.com/repos/KoelnAPI/kvb-api/contributors", 
        "html_url": "https://github.com/KoelnAPI/kvb-api", 
        "forks": 2, 
        "compare_url": "https://api.github.com/repos/KoelnAPI/kvb-api/compare/{base}...{head}", 
        "open_issues": 0, 
        "git_url": "git://github.com/KoelnAPI/kvb-api.git", 
        "svn_url": "https://github.com/KoelnAPI/kvb-api", 
        "merges_url": "https://api.github.com/repos/KoelnAPI/kvb-api/merges", 
        "has_issues": true, 
        "ssh_url": "git@github.com:KoelnAPI/kvb-api.git", 
        "blobs_url": "https://api.github.com/repos/KoelnAPI/kvb-api/git/blobs{/sha}", 
        "git_commits_url": "https://api.github.com/repos/KoelnAPI/kvb-api/git/commits{/sha}", 
        "hooks_url": "https://api.github.com/repos/KoelnAPI/kvb-api/hooks", 
        "has_downloads": true, 
        "watchers": 0, 
        "name": "kvb-api", 
        "language": "Python", 
        "url": "https://api.github.com/repos/KoelnAPI/kvb-api", 
        "created_at": "2014-05-30T13:41:00Z", 
        "pushed_at": "2015-11-27T15:51:55Z", 
        "forks_count": 2, 
        "default_branch": "master", 
        "teams_url": "https://api.github.com/repos/KoelnAPI/kvb-api/teams", 
        "trees_url": "https://api.github.com/repos/KoelnAPI/kvb-api/git/trees{/sha}", 
        "branches_url": "https://api.github.com/repos/KoelnAPI/kvb-api/branches{/branch}", 
        "subscribers_url": "https://api.github.com/repos/KoelnAPI/kvb-api/subscribers", 
        "permissions": {
            "admin": false, 
            "push": false, 
            "pull": true
        }, 
        "stargazers_url": "https://api.github.com/repos/KoelnAPI/kvb-api/stargazers"
    }, 
    {
        "issues_url": "https://api.github.com/repos/KoelnAPI/kvb-status/issues{/number}", 
        "deployments_url": "https://api.github.com/repos/KoelnAPI/kvb-status/deployments", 
        "stargazers_count": 2, 
        "forks_url": "https://api.github.com/repos/KoelnAPI/kvb-status/forks", 
        "mirror_url": null, 
        "subscription_url": "https://api.github.com/repos/KoelnAPI/kvb-status/subscription", 
        "notifications_url": "https://api.github.com/repos/KoelnAPI/kvb-status/notifications{?since,all,participating}", 
        "collaborators_url": "https://api.github.com/repos/KoelnAPI/kvb-status/collaborators{/collaborator}", 
        "updated_at": "2015-03-13T12:15:00Z", 
        "private": false, 
        "pulls_url": "https://api.github.com/repos/KoelnAPI/kvb-status/pulls{/number}", 
        "issue_comment_url": "https://api.github.com/repos/KoelnAPI/kvb-status/issues/comments{/number}", 
        "labels_url": "https://api.github.com/repos/KoelnAPI/kvb-status/labels{/name}", 
        "has_wiki": true, 
        "full_name": "KoelnAPI/kvb-status", 
        "owner": {
            "following_url": "https://api.github.com/users/KoelnAPI/following{/other_user}", 
            "events_url": "https://api.github.com/users/KoelnAPI/events{/privacy}", 
            "organizations_url": "https://api.github.com/users/KoelnAPI/orgs", 
            "url": "https://api.github.com/users/KoelnAPI", 
            "gists_url": "https://api.github.com/users/KoelnAPI/gists{/gist_id}", 
            "html_url": "https://github.com/KoelnAPI", 
            "subscriptions_url": "https://api.github.com/users/KoelnAPI/subscriptions", 
            "avatar_url": "https://avatars.githubusercontent.com/u/5716567?v=3", 
            "repos_url": "https://api.github.com/users/KoelnAPI/repos", 
            "received_events_url": "https://api.github.com/users/KoelnAPI/received_events", 
            "gravatar_id": "", 
            "starred_url": "https://api.github.com/users/KoelnAPI/starred{/owner}{/repo}", 
            "site_admin": false, 
            "login": "KoelnAPI", 
            "type": "Organization", 
            "id": 5716567, 
            "followers_url": "https://api.github.com/users/KoelnAPI/followers"
        }, 
        "statuses_url": "https://api.github.com/repos/KoelnAPI/kvb-status/statuses/{sha}", 
        "id": 16722354, 
        "keys_url": "https://api.github.com/repos/KoelnAPI/kvb-status/keys{/key_id}", 
        "description": "Status and disruption messages from KVB K\u00f6ln, delivered mobile-friendly", 
        "tags_url": "https://api.github.com/repos/KoelnAPI/kvb-status/tags", 
        "downloads_url": "https://api.github.com/repos/KoelnAPI/kvb-status/downloads", 
        "assignees_url": "https://api.github.com/repos/KoelnAPI/kvb-status/assignees{/user}", 
        "contents_url": "https://api.github.com/repos/KoelnAPI/kvb-status/contents/{+path}", 
        "has_pages": false, 
        "git_refs_url": "https://api.github.com/repos/KoelnAPI/kvb-status/git/refs{/sha}", 
        "open_issues_count": 0, 
        "clone_url": "https://github.com/KoelnAPI/kvb-status.git", 
        "watchers_count": 2, 
        "git_tags_url": "https://api.github.com/repos/KoelnAPI/kvb-status/git/tags{/sha}", 
        "milestones_url": "https://api.github.com/repos/KoelnAPI/kvb-status/milestones{/number}", 
        "languages_url": "https://api.github.com/repos/KoelnAPI/kvb-status/languages", 
        "size": 268, 
        "homepage": null, 
        "fork": false, 
        "commits_url": "https://api.github.com/repos/KoelnAPI/kvb-status/commits{/sha}", 
        "releases_url": "https://api.github.com/repos/KoelnAPI/kvb-status/releases{/id}", 
        "issue_events_url": "https://api.github.com/repos/KoelnAPI/kvb-status/issues/events{/number}", 
        "archive_url": "https://api.github.com/repos/KoelnAPI/kvb-status/{archive_format}{/ref}", 
        "comments_url": "https://api.github.com/repos/KoelnAPI/kvb-status/comments{/number}", 
        "events_url": "https://api.github.com/repos/KoelnAPI/kvb-status/events", 
        "contributors_url": "https://api.github.com/repos/KoelnAPI/kvb-status/contributors", 
        "html_url": "https://github.com/KoelnAPI/kvb-status", 
        "forks": 0, 
        "compare_url": "https://api.github.com/repos/KoelnAPI/kvb-status/compare/{base}...{head}", 
        "open_issues": 0, 
        "git_url": "git://github.com/KoelnAPI/kvb-status.git", 
        "svn_url": "https://github.com/KoelnAPI/kvb-status", 
        "merges_url": "https://api.github.com/repos/KoelnAPI/kvb-status/merges", 
        "has_issues": true, 
        "ssh_url": "git@github.com:KoelnAPI/kvb-status.git", 
        "blobs_url": "https://api.github.com/repos/KoelnAPI/kvb-status/git/blobs{/sha}", 
        "git_commits_url": "https://api.github.com/repos/KoelnAPI/kvb-status/git/commits{/sha}", 
        "hooks_url": "https://api.github.com/repos/KoelnAPI/kvb-status/hooks", 
        "has_downloads": true, 
        "watchers": 2, 
        "name": "kvb-status", 
        "language": null, 
        "url": "https://api.github.com/repos/KoelnAPI/kvb-status", 
        "created_at": "2014-02-11T07:00:42Z", 
        "pushed_at": "2014-06-24T14:50:45Z", 
        "forks_count": 0, 
        "default_branch": "master", 
        "teams_url": "https://api.github.com/repos/KoelnAPI/kvb-status/teams", 
        "trees_url": "https://api.github.com/repos/KoelnAPI/kvb-status/git/trees{/sha}", 
        "branches_url": "https://api.github.com/repos/KoelnAPI/kvb-status/branches{/branch}", 
        "subscribers_url": "https://api.github.com/repos/KoelnAPI/kvb-status/subscribers", 
        "permissions": {
            "admin": false, 
            "push": false, 
            "pull": true
        }, 
        "stargazers_url": "https://api.github.com/repos/KoelnAPI/kvb-status/stargazers"
    }, 
    {
        "issues_url": "https://api.github.com/repos/KoelnAPI/opendataday-koeln/issues{/number}", 
        "deployments_url": "https://api.github.com/repos/KoelnAPI/opendataday-koeln/deployments", 
        "stargazers_count": 0, 
        "forks_url": "https://api.github.com/repos/KoelnAPI/opendataday-koeln/forks", 
        "mirror_url": null, 
        "subscription_url": "https://api.github.com/repos/KoelnAPI/opendataday-koeln/subscription", 
        "notifications_url": "https://api.github.com/repos/KoelnAPI/opendataday-koeln/notifications{?since,all,participating}", 
        "collaborators_url": "https://api.github.com/repos/KoelnAPI/opendataday-koeln/collaborators{/collaborator}", 
        "updated_at": "2015-05-30T20:21:03Z", 
        "private": false, 
        "pulls_url": "https://api.github.com/repos/KoelnAPI/opendataday-koeln/pulls{/number}", 
        "issue_comment_url": "https://api.github.com/repos/KoelnAPI/opendataday-koeln/issues/comments{/number}", 
        "labels_url": "https://api.github.com/repos/KoelnAPI/opendataday-koeln/labels{/name}", 
        "has_wiki": true, 
        "full_name": "KoelnAPI/opendataday-koeln", 
        "owner": {
            "following_url": "https://api.github.com/users/KoelnAPI/following{/other_user}", 
            "events_url": "https://api.github.com/users/KoelnAPI/events{/privacy}", 
            "organizations_url": "https://api.github.com/users/KoelnAPI/orgs", 
            "url": "https://api.github.com/users/KoelnAPI", 
            "gists_url": "https://api.github.com/users/KoelnAPI/gists{/gist_id}", 
            "html_url": "https://github.com/KoelnAPI", 
            "subscriptions_url": "https://api.github.com/users/KoelnAPI/subscriptions", 
            "avatar_url": "https://avatars.githubusercontent.com/u/5716567?v=3", 
            "repos_url": "https://api.github.com/users/KoelnAPI/repos", 
            "received_events_url": "https://api.github.com/users/KoelnAPI/received_events", 
            "gravatar_id": "", 
            "starred_url": "https://api.github.com/users/KoelnAPI/starred{/owner}{/repo}", 
            "site_admin": false, 
            "login": "KoelnAPI", 
            "type": "Organization", 
            "id": 5716567, 
            "followers_url": "https://api.github.com/users/KoelnAPI/followers"
        }, 
        "statuses_url": "https://api.github.com/repos/KoelnAPI/opendataday-koeln/statuses/{sha}", 
        "id": 7556547, 
        "keys_url": "https://api.github.com/repos/KoelnAPI/opendataday-koeln/keys{/key_id}", 
        "description": "Open Data Day K\u00f6ln Website und evtl. mehr", 
        "tags_url": "https://api.github.com/repos/KoelnAPI/opendataday-koeln/tags", 
        "downloads_url": "https://api.github.com/repos/KoelnAPI/opendataday-koeln/downloads", 
        "assignees_url": "https://api.github.com/repos/KoelnAPI/opendataday-koeln/assignees{/user}", 
        "contents_url": "https://api.github.com/repos/KoelnAPI/opendataday-koeln/contents/{+path}", 
        "has_pages": false, 
        "git_refs_url": "https://api.github.com/repos/KoelnAPI/opendataday-koeln/git/refs{/sha}", 
        "open_issues_count": 0, 
        "clone_url": "https://github.com/KoelnAPI/opendataday-koeln.git", 
        "watchers_count": 0, 
        "git_tags_url": "https://api.github.com/repos/KoelnAPI/opendataday-koeln/git/tags{/sha}", 
        "milestones_url": "https://api.github.com/repos/KoelnAPI/opendataday-koeln/milestones{/number}", 
        "languages_url": "https://api.github.com/repos/KoelnAPI/opendataday-koeln/languages", 
        "size": 1032, 
        "homepage": null, 
        "fork": false, 
        "commits_url": "https://api.github.com/repos/KoelnAPI/opendataday-koeln/commits{/sha}", 
        "releases_url": "https://api.github.com/repos/KoelnAPI/opendataday-koeln/releases{/id}", 
        "issue_events_url": "https://api.github.com/repos/KoelnAPI/opendataday-koeln/issues/events{/number}", 
        "archive_url": "https://api.github.com/repos/KoelnAPI/opendataday-koeln/{archive_format}{/ref}", 
        "comments_url": "https://api.github.com/repos/KoelnAPI/opendataday-koeln/comments{/number}", 
        "events_url": "https://api.github.com/repos/KoelnAPI/opendataday-koeln/events", 
        "contributors_url": "https://api.github.com/repos/KoelnAPI/opendataday-koeln/contributors", 
        "html_url": "https://github.com/KoelnAPI/opendataday-koeln", 
        "forks": 0, 
        "compare_url": "https://api.github.com/repos/KoelnAPI/opendataday-koeln/compare/{base}...{head}", 
        "open_issues": 0, 
        "git_url": "git://github.com/KoelnAPI/opendataday-koeln.git", 
        "svn_url": "https://github.com/KoelnAPI/opendataday-koeln", 
        "merges_url": "https://api.github.com/repos/KoelnAPI/opendataday-koeln/merges", 
        "has_issues": true, 
        "ssh_url": "git@github.com:KoelnAPI/opendataday-koeln.git", 
        "blobs_url": "https://api.github.com/repos/KoelnAPI/opendataday-koeln/git/blobs{/sha}", 
        "git_commits_url": "https://api.github.com/repos/KoelnAPI/opendataday-koeln/git/commits{/sha}", 
        "hooks_url": "https://api.github.com/repos/KoelnAPI/opendataday-koeln/hooks", 
        "has_downloads": true, 
        "watchers": 0, 
        "name": "opendataday-koeln", 
        "language": "JavaScript", 
        "url": "https://api.github.com/repos/KoelnAPI/opendataday-koeln", 
        "created_at": "2013-01-11T08:30:18Z", 
        "pushed_at": "2013-02-22T08:39:20Z", 
        "forks_count": 0, 
        "default_branch": "master", 
        "teams_url": "https://api.github.com/repos/KoelnAPI/opendataday-koeln/teams", 
        "trees_url": "https://api.github.com/repos/KoelnAPI/opendataday-koeln/git/trees{/sha}", 
        "branches_url": "https://api.github.com/repos/KoelnAPI/opendataday-koeln/branches{/branch}", 
        "subscribers_url": "https://api.github.com/repos/KoelnAPI/opendataday-koeln/subscribers", 
        "permissions": {
            "admin": false, 
            "push": false, 
            "pull": true
        }, 
        "stargazers_url": "https://api.github.com/repos/KoelnAPI/opendataday-koeln/stargazers"
    }, 
    {
        "issues_url": "https://api.github.com/repos/KoelnAPI/vrs-scraper/issues{/number}", 
        "deployments_url": "https://api.github.com/repos/KoelnAPI/vrs-scraper/deployments", 
        "stargazers_count": 0, 
        "forks_url": "https://api.github.com/repos/KoelnAPI/vrs-scraper/forks", 
        "mirror_url": null, 
        "subscription_url": "https://api.github.com/repos/KoelnAPI/vrs-scraper/subscription", 
        "notifications_url": "https://api.github.com/repos/KoelnAPI/vrs-scraper/notifications{?since,all,participating}", 
        "collaborators_url": "https://api.github.com/repos/KoelnAPI/vrs-scraper/collaborators{/collaborator}", 
        "updated_at": "2014-06-02T20:53:54Z", 
        "private": false, 
        "pulls_url": "https://api.github.com/repos/KoelnAPI/vrs-scraper/pulls{/number}", 
        "issue_comment_url": "https://api.github.com/repos/KoelnAPI/vrs-scraper/issues/comments{/number}", 
        "labels_url": "https://api.github.com/repos/KoelnAPI/vrs-scraper/labels{/name}", 
        "has_wiki": true, 
        "full_name": "KoelnAPI/vrs-scraper", 
        "owner": {
            "following_url": "https://api.github.com/users/KoelnAPI/following{/other_user}", 
            "events_url": "https://api.github.com/users/KoelnAPI/events{/privacy}", 
            "organizations_url": "https://api.github.com/users/KoelnAPI/orgs", 
            "url": "https://api.github.com/users/KoelnAPI", 
            "gists_url": "https://api.github.com/users/KoelnAPI/gists{/gist_id}", 
            "html_url": "https://github.com/KoelnAPI", 
            "subscriptions_url": "https://api.github.com/users/KoelnAPI/subscriptions", 
            "avatar_url": "https://avatars.githubusercontent.com/u/5716567?v=3", 
            "repos_url": "https://api.github.com/users/KoelnAPI/repos", 
            "received_events_url": "https://api.github.com/users/KoelnAPI/received_events", 
            "gravatar_id": "", 
            "starred_url": "https://api.github.com/users/KoelnAPI/starred{/owner}{/repo}", 
            "site_admin": false, 
            "login": "KoelnAPI", 
            "type": "Organization", 
            "id": 5716567, 
            "followers_url": "https://api.github.com/users/KoelnAPI/followers"
        }, 
        "statuses_url": "https://api.github.com/repos/KoelnAPI/vrs-scraper/statuses/{sha}", 
        "id": 17062136, 
        "keys_url": "https://api.github.com/repos/KoelnAPI/vrs-scraper/keys{/key_id}", 
        "description": "Scrapes station information from VRS (vrsinfo.de)", 
        "tags_url": "https://api.github.com/repos/KoelnAPI/vrs-scraper/tags", 
        "downloads_url": "https://api.github.com/repos/KoelnAPI/vrs-scraper/downloads", 
        "assignees_url": "https://api.github.com/repos/KoelnAPI/vrs-scraper/assignees{/user}", 
        "contents_url": "https://api.github.com/repos/KoelnAPI/vrs-scraper/contents/{+path}", 
        "has_pages": false, 
        "git_refs_url": "https://api.github.com/repos/KoelnAPI/vrs-scraper/git/refs{/sha}", 
        "open_issues_count": 0, 
        "clone_url": "https://github.com/KoelnAPI/vrs-scraper.git", 
        "watchers_count": 0, 
        "git_tags_url": "https://api.github.com/repos/KoelnAPI/vrs-scraper/git/tags{/sha}", 
        "milestones_url": "https://api.github.com/repos/KoelnAPI/vrs-scraper/milestones{/number}", 
        "languages_url": "https://api.github.com/repos/KoelnAPI/vrs-scraper/languages", 
        "size": 268, 
        "homepage": null, 
        "fork": false, 
        "commits_url": "https://api.github.com/repos/KoelnAPI/vrs-scraper/commits{/sha}", 
        "releases_url": "https://api.github.com/repos/KoelnAPI/vrs-scraper/releases{/id}", 
        "issue_events_url": "https://api.github.com/repos/KoelnAPI/vrs-scraper/issues/events{/number}", 
        "archive_url": "https://api.github.com/repos/KoelnAPI/vrs-scraper/{archive_format}{/ref}", 
        "comments_url": "https://api.github.com/repos/KoelnAPI/vrs-scraper/comments{/number}", 
        "events_url": "https://api.github.com/repos/KoelnAPI/vrs-scraper/events", 
        "contributors_url": "https://api.github.com/repos/KoelnAPI/vrs-scraper/contributors", 
        "html_url": "https://github.com/KoelnAPI/vrs-scraper", 
        "forks": 0, 
        "compare_url": "https://api.github.com/repos/KoelnAPI/vrs-scraper/compare/{base}...{head}", 
        "open_issues": 0, 
        "git_url": "git://github.com/KoelnAPI/vrs-scraper.git", 
        "svn_url": "https://github.com/KoelnAPI/vrs-scraper", 
        "merges_url": "https://api.github.com/repos/KoelnAPI/vrs-scraper/merges", 
        "has_issues": true, 
        "ssh_url": "git@github.com:KoelnAPI/vrs-scraper.git", 
        "blobs_url": "https://api.github.com/repos/KoelnAPI/vrs-scraper/git/blobs{/sha}", 
        "git_commits_url": "https://api.github.com/repos/KoelnAPI/vrs-scraper/git/commits{/sha}", 
        "hooks_url": "https://api.github.com/repos/KoelnAPI/vrs-scraper/hooks", 
        "has_downloads": true, 
        "watchers": 0, 
        "name": "vrs-scraper", 
        "language": "Python", 
        "url": "https://api.github.com/repos/KoelnAPI/vrs-scraper", 
        "created_at": "2014-02-21T16:25:53Z", 
        "pushed_at": "2014-06-02T20:53:54Z", 
        "forks_count": 0, 
        "default_branch": "master", 
        "teams_url": "https://api.github.com/repos/KoelnAPI/vrs-scraper/teams", 
        "trees_url": "https://api.github.com/repos/KoelnAPI/vrs-scraper/git/trees{/sha}", 
        "branches_url": "https://api.github.com/repos/KoelnAPI/vrs-scraper/branches{/branch}", 
        "subscribers_url": "https://api.github.com/repos/KoelnAPI/vrs-scraper/subscribers", 
        "permissions": {
            "admin": false, 
            "push": false, 
            "pull": true
        }, 
        "stargazers_url": "https://api.github.com/repos/KoelnAPI/vrs-scraper/stargazers"
    }, 
    {
        "issues_url": "https://api.github.com/repos/KoelnAPI/Wiki/issues{/number}", 
        "deployments_url": "https://api.github.com/repos/KoelnAPI/Wiki/deployments", 
        "stargazers_count": 0, 
        "forks_url": "https://api.github.com/repos/KoelnAPI/Wiki/forks", 
        "mirror_url": null, 
        "subscription_url": "https://api.github.com/repos/KoelnAPI/Wiki/subscription", 
        "notifications_url": "https://api.github.com/repos/KoelnAPI/Wiki/notifications{?since,all,participating}", 
        "collaborators_url": "https://api.github.com/repos/KoelnAPI/Wiki/collaborators{/collaborator}", 
        "updated_at": "2015-03-23T21:41:43Z", 
        "private": false, 
        "pulls_url": "https://api.github.com/repos/KoelnAPI/Wiki/pulls{/number}", 
        "issue_comment_url": "https://api.github.com/repos/KoelnAPI/Wiki/issues/comments{/number}", 
        "labels_url": "https://api.github.com/repos/KoelnAPI/Wiki/labels{/name}", 
        "has_wiki": true, 
        "full_name": "KoelnAPI/Wiki", 
        "owner": {
            "following_url": "https://api.github.com/users/KoelnAPI/following{/other_user}", 
            "events_url": "https://api.github.com/users/KoelnAPI/events{/privacy}", 
            "organizations_url": "https://api.github.com/users/KoelnAPI/orgs", 
            "url": "https://api.github.com/users/KoelnAPI", 
            "gists_url": "https://api.github.com/users/KoelnAPI/gists{/gist_id}", 
            "html_url": "https://github.com/KoelnAPI", 
            "subscriptions_url": "https://api.github.com/users/KoelnAPI/subscriptions", 
            "avatar_url": "https://avatars.githubusercontent.com/u/5716567?v=3", 
            "repos_url": "https://api.github.com/users/KoelnAPI/repos", 
            "received_events_url": "https://api.github.com/users/KoelnAPI/received_events", 
            "gravatar_id": "", 
            "starred_url": "https://api.github.com/users/KoelnAPI/starred{/owner}{/repo}", 
            "site_admin": false, 
            "login": "KoelnAPI", 
            "type": "Organization", 
            "id": 5716567, 
            "followers_url": "https://api.github.com/users/KoelnAPI/followers"
        }, 
        "statuses_url": "https://api.github.com/repos/KoelnAPI/Wiki/statuses/{sha}", 
        "id": 31683574, 
        "keys_url": "https://api.github.com/repos/KoelnAPI/Wiki/keys{/key_id}", 
        "description": "The general purpose K\u00f6ln API Wiki", 
        "tags_url": "https://api.github.com/repos/KoelnAPI/Wiki/tags", 
        "downloads_url": "https://api.github.com/repos/KoelnAPI/Wiki/downloads", 
        "assignees_url": "https://api.github.com/repos/KoelnAPI/Wiki/assignees{/user}", 
        "contents_url": "https://api.github.com/repos/KoelnAPI/Wiki/contents/{+path}", 
        "has_pages": false, 
        "git_refs_url": "https://api.github.com/repos/KoelnAPI/Wiki/git/refs{/sha}", 
        "open_issues_count": 0, 
        "clone_url": "https://github.com/KoelnAPI/Wiki.git", 
        "watchers_count": 0, 
        "git_tags_url": "https://api.github.com/repos/KoelnAPI/Wiki/git/tags{/sha}", 
        "milestones_url": "https://api.github.com/repos/KoelnAPI/Wiki/milestones{/number}", 
        "languages_url": "https://api.github.com/repos/KoelnAPI/Wiki/languages", 
        "size": 372, 
        "homepage": null, 
        "fork": false, 
        "commits_url": "https://api.github.com/repos/KoelnAPI/Wiki/commits{/sha}", 
        "releases_url": "https://api.github.com/repos/KoelnAPI/Wiki/releases{/id}", 
        "issue_events_url": "https://api.github.com/repos/KoelnAPI/Wiki/issues/events{/number}", 
        "archive_url": "https://api.github.com/repos/KoelnAPI/Wiki/{archive_format}{/ref}", 
        "comments_url": "https://api.github.com/repos/KoelnAPI/Wiki/comments{/number}", 
        "events_url": "https://api.github.com/repos/KoelnAPI/Wiki/events", 
        "contributors_url": "https://api.github.com/repos/KoelnAPI/Wiki/contributors", 
        "html_url": "https://github.com/KoelnAPI/Wiki", 
        "forks": 1, 
        "compare_url": "https://api.github.com/repos/KoelnAPI/Wiki/compare/{base}...{head}", 
        "open_issues": 0, 
        "git_url": "git://github.com/KoelnAPI/Wiki.git", 
        "svn_url": "https://github.com/KoelnAPI/Wiki", 
        "merges_url": "https://api.github.com/repos/KoelnAPI/Wiki/merges", 
        "has_issues": false, 
        "ssh_url": "git@github.com:KoelnAPI/Wiki.git", 
        "blobs_url": "https://api.github.com/repos/KoelnAPI/Wiki/git/blobs{/sha}", 
        "git_commits_url": "https://api.github.com/repos/KoelnAPI/Wiki/git/commits{/sha}", 
        "hooks_url": "https://api.github.com/repos/KoelnAPI/Wiki/hooks", 
        "has_downloads": true, 
        "watchers": 0, 
        "name": "Wiki", 
        "language": "HTML", 
        "url": "https://api.github.com/repos/KoelnAPI/Wiki", 
        "created_at": "2015-03-04T22:34:19Z", 
        "pushed_at": "2015-03-23T21:41:43Z", 
        "forks_count": 1, 
        "default_branch": "master", 
        "teams_url": "https://api.github.com/repos/KoelnAPI/Wiki/teams", 
        "trees_url": "https://api.github.com/repos/KoelnAPI/Wiki/git/trees{/sha}", 
        "branches_url": "https://api.github.com/repos/KoelnAPI/Wiki/branches{/branch}", 
        "subscribers_url": "https://api.github.com/repos/KoelnAPI/Wiki/subscribers", 
        "permissions": {
            "admin": false, 
            "push": false, 
            "pull": true
        }, 
        "stargazers_url": "https://api.github.com/repos/KoelnAPI/Wiki/stargazers"
    }
]