[
    {
        "following_url": "https://api.github.com/users/chokkoyamada/following{/other_user}", 
        "events_url": "https://api.github.com/users/chokkoyamada/events{/privacy}", 
        "organizations_url": "https://api.github.com/users/chokkoyamada/orgs", 
        "url": "https://api.github.com/users/chokkoyamada", 
        "gists_url": "https://api.github.com/users/chokkoyamada/gists{/gist_id}", 
        "html_url": "https://github.com/chokkoyamada", 
        "subscriptions_url": "https://api.github.com/users/chokkoyamada/subscriptions", 
        "avatar_url": "https://avatars.githubusercontent.com/u/843192?v=3", 
        "repos_url": "https://api.github.com/users/chokkoyamada/repos", 
        "received_events_url": "https://api.github.com/users/chokkoyamada/received_events", 
        "gravatar_id": "", 
        "starred_url": "https://api.github.com/users/chokkoyamada/starred{/owner}{/repo}", 
        "site_admin": false, 
        "login": "chokkoyamada", 
        "type": "User", 
        "id": 843192, 
        "followers_url": "https://api.github.com/users/chokkoyamada/followers"
    }, 
    {
        "following_url": "https://api.github.com/users/F88/following{/other_user}", 
        "events_url": "https://api.github.com/users/F88/events{/privacy}", 
        "organizations_url": "https://api.github.com/users/F88/orgs", 
        "url": "https://api.github.com/users/F88", 
        "gists_url": "https://api.github.com/users/F88/gists{/gist_id}", 
        "html_url": "https://github.com/F88", 
        "subscriptions_url": "https://api.github.com/users/F88/subscriptions", 
        "avatar_url": "https://avatars.githubusercontent.com/u/685250?v=3", 
        "repos_url": "https://api.github.com/users/F88/repos", 
        "received_events_url": "https://api.github.com/users/F88/received_events", 
        "gravatar_id": "", 
        "starred_url": "https://api.github.com/users/F88/starred{/owner}{/repo}", 
        "site_admin": false, 
        "login": "F88", 
        "type": "User", 
        "id": 685250, 
        "followers_url": "https://api.github.com/users/F88/followers"
    }, 
    {
        "following_url": "https://api.github.com/users/halsk/following{/other_user}", 
        "events_url": "https://api.github.com/users/halsk/events{/privacy}", 
        "organizations_url": "https://api.github.com/users/halsk/orgs", 
        "url": "https://api.github.com/users/halsk", 
        "gists_url": "https://api.github.com/users/halsk/gists{/gist_id}", 
        "html_url": "https://github.com/halsk", 
        "subscriptions_url": "https://api.github.com/users/halsk/subscriptions", 
        "avatar_url": "https://avatars.githubusercontent.com/u/16509?v=3", 
        "repos_url": "https://api.github.com/users/halsk/repos", 
        "received_events_url": "https://api.github.com/users/halsk/received_events", 
        "gravatar_id": "", 
        "starred_url": "https://api.github.com/users/halsk/starred{/owner}{/repo}", 
        "site_admin": false, 
        "login": "halsk", 
        "type": "User", 
        "id": 16509, 
        "followers_url": "https://api.github.com/users/halsk/followers"
    }, 
    {
        "following_url": "https://api.github.com/users/KuNi1138/following{/other_user}", 
        "events_url": "https://api.github.com/users/KuNi1138/events{/privacy}", 
        "organizations_url": "https://api.github.com/users/KuNi1138/orgs", 
        "url": "https://api.github.com/users/KuNi1138", 
        "gists_url": "https://api.github.com/users/KuNi1138/gists{/gist_id}", 
        "html_url": "https://github.com/KuNi1138", 
        "subscriptions_url": "https://api.github.com/users/KuNi1138/subscriptions", 
        "avatar_url": "https://avatars.githubusercontent.com/u/18309757?v=3", 
        "repos_url": "https://api.github.com/users/KuNi1138/repos", 
        "received_events_url": "https://api.github.com/users/KuNi1138/received_events", 
        "gravatar_id": "", 
        "starred_url": "https://api.github.com/users/KuNi1138/starred{/owner}{/repo}", 
        "site_admin": false, 
        "login": "KuNi1138", 
        "type": "User", 
        "id": 18309757, 
        "followers_url": "https://api.github.com/users/KuNi1138/followers"
    }, 
    {
        "following_url": "https://api.github.com/users/n1n9-jp/following{/other_user}", 
        "events_url": "https://api.github.com/users/n1n9-jp/events{/privacy}", 
        "organizations_url": "https://api.github.com/users/n1n9-jp/orgs", 
        "url": "https://api.github.com/users/n1n9-jp", 
        "gists_url": "https://api.github.com/users/n1n9-jp/gists{/gist_id}", 
        "html_url": "https://github.com/n1n9-jp", 
        "subscriptions_url": "https://api.github.com/users/n1n9-jp/subscriptions", 
        "avatar_url": "https://avatars.githubusercontent.com/u/974276?v=3", 
        "repos_url": "https://api.github.com/users/n1n9-jp/repos", 
        "received_events_url": "https://api.github.com/users/n1n9-jp/received_events", 
        "gravatar_id": "", 
        "starred_url": "https://api.github.com/users/n1n9-jp/starred{/owner}{/repo}", 
        "site_admin": false, 
        "login": "n1n9-jp", 
        "type": "User", 
        "id": 974276, 
        "followers_url": "https://api.github.com/users/n1n9-jp/followers"
    }, 
    {
        "following_url": "https://api.github.com/users/nkawa/following{/other_user}", 
        "events_url": "https://api.github.com/users/nkawa/events{/privacy}", 
        "organizations_url": "https://api.github.com/users/nkawa/orgs", 
        "url": "https://api.github.com/users/nkawa", 
        "gists_url": "https://api.github.com/users/nkawa/gists{/gist_id}", 
        "html_url": "https://github.com/nkawa", 
        "subscriptions_url": "https://api.github.com/users/nkawa/subscriptions", 
        "avatar_url": "https://avatars.githubusercontent.com/u/254385?v=3", 
        "repos_url": "https://api.github.com/users/nkawa/repos", 
        "received_events_url": "https://api.github.com/users/nkawa/received_events", 
        "gravatar_id": "", 
        "starred_url": "https://api.github.com/users/nkawa/starred{/owner}{/repo}", 
        "site_admin": false, 
        "login": "nkawa", 
        "type": "User", 
        "id": 254385, 
        "followers_url": "https://api.github.com/users/nkawa/followers"
    }, 
    {
        "following_url": "https://api.github.com/users/tosato3/following{/other_user}", 
        "events_url": "https://api.github.com/users/tosato3/events{/privacy}", 
        "organizations_url": "https://api.github.com/users/tosato3/orgs", 
        "url": "https://api.github.com/users/tosato3", 
        "gists_url": "https://api.github.com/users/tosato3/gists{/gist_id}", 
        "html_url": "https://github.com/tosato3", 
        "subscriptions_url": "https://api.github.com/users/tosato3/subscriptions", 
        "avatar_url": "https://avatars.githubusercontent.com/u/4838011?v=3", 
        "repos_url": "https://api.github.com/users/tosato3/repos", 
        "received_events_url": "https://api.github.com/users/tosato3/received_events", 
        "gravatar_id": "", 
        "starred_url": "https://api.github.com/users/tosato3/starred{/owner}{/repo}", 
        "site_admin": false, 
        "login": "tosato3", 
        "type": "User", 
        "id": 4838011, 
        "followers_url": "https://api.github.com/users/tosato3/followers"
    }, 
    {
        "following_url": "https://api.github.com/users/yoichigmf/following{/other_user}", 
        "events_url": "https://api.github.com/users/yoichigmf/events{/privacy}", 
        "organizations_url": "https://api.github.com/users/yoichigmf/orgs", 
        "url": "https://api.github.com/users/yoichigmf", 
        "gists_url": "https://api.github.com/users/yoichigmf/gists{/gist_id}", 
        "html_url": "https://github.com/yoichigmf", 
        "subscriptions_url": "https://api.github.com/users/yoichigmf/subscriptions", 
        "avatar_url": "https://avatars.githubusercontent.com/u/327016?v=3", 
        "repos_url": "https://api.github.com/users/yoichigmf/repos", 
        "received_events_url": "https://api.github.com/users/yoichigmf/received_events", 
        "gravatar_id": "", 
        "starred_url": "https://api.github.com/users/yoichigmf/starred{/owner}{/repo}", 
        "site_admin": false, 
        "login": "yoichigmf", 
        "type": "User", 
        "id": 327016, 
        "followers_url": "https://api.github.com/users/yoichigmf/followers"
    }
]