[
    {
        "issues_url": "https://api.github.com/orgs/nko4/issues", 
        "members_url": "https://api.github.com/orgs/nko4/members{/member}", 
        "description": null, 
        "public_members_url": "https://api.github.com/orgs/nko4/public_members{/member}", 
        "url": "https://api.github.com/orgs/nko4", 
        "events_url": "https://api.github.com/orgs/nko4/events", 
        "avatar_url": "https://avatars.githubusercontent.com/u/3877928?v=3", 
        "repos_url": "https://api.github.com/orgs/nko4/repos", 
        "login": "nko4", 
        "id": 3877928, 
        "hooks_url": "https://api.github.com/orgs/nko4/hooks"
    }, 
    {
        "issues_url": "https://api.github.com/orgs/codeforpakistan/issues", 
        "members_url": "https://api.github.com/orgs/codeforpakistan/members{/member}", 
        "description": "", 
        "public_members_url": "https://api.github.com/orgs/codeforpakistan/public_members{/member}", 
        "url": "https://api.github.com/orgs/codeforpakistan", 
        "events_url": "https://api.github.com/orgs/codeforpakistan/events", 
        "avatar_url": "https://avatars.githubusercontent.com/u/4421892?v=3", 
        "repos_url": "https://api.github.com/orgs/codeforpakistan/repos", 
        "login": "codeforpakistan", 
        "id": 4421892, 
        "hooks_url": "https://api.github.com/orgs/codeforpakistan/hooks"
    }, 
    {
        "issues_url": "https://api.github.com/orgs/creanyx/issues", 
        "members_url": "https://api.github.com/orgs/creanyx/members{/member}", 
        "description": "A web solutions provider company with special emphasis on SMS and VOIP based applications.", 
        "public_members_url": "https://api.github.com/orgs/creanyx/public_members{/member}", 
        "url": "https://api.github.com/orgs/creanyx", 
        "events_url": "https://api.github.com/orgs/creanyx/events", 
        "avatar_url": "https://avatars.githubusercontent.com/u/7057404?v=3", 
        "repos_url": "https://api.github.com/orgs/creanyx/repos", 
        "login": "creanyx", 
        "id": 7057404, 
        "hooks_url": "https://api.github.com/orgs/creanyx/hooks"
    }
]