{
    "public_repos": 43, 
    "site_admin": false, 
    "subscriptions_url": "https://api.github.com/users/erasme/subscriptions", 
    "gravatar_id": "", 
    "hireable": null, 
    "id": 204704, 
    "followers_url": "https://api.github.com/users/erasme/followers", 
    "following_url": "https://api.github.com/users/erasme/following{/other_user}", 
    "blog": "http://erasme.org", 
    "followers": 0, 
    "location": "Saint Cl\u00e9ment les Places, Rh\u00f4ne, France", 
    "type": "Organization", 
    "email": null, 
    "bio": null, 
    "gists_url": "https://api.github.com/users/erasme/gists{/gist_id}", 
    "company": null, 
    "events_url": "https://api.github.com/users/erasme/events{/privacy}", 
    "html_url": "https://github.com/erasme", 
    "updated_at": "2016-02-26T23:01:22Z", 
    "received_events_url": "https://api.github.com/users/erasme/received_events", 
    "starred_url": "https://api.github.com/users/erasme/starred{/owner}{/repo}", 
    "public_gists": 0, 
    "name": "Centre Multim\u00e9dia ERASME", 
    "organizations_url": "https://api.github.com/users/erasme/orgs", 
    "url": "https://api.github.com/users/erasme", 
    "created_at": "2010-02-16T16:27:05Z", 
    "avatar_url": "https://avatars.githubusercontent.com/u/204704?v=3", 
    "repos_url": "https://api.github.com/users/erasme/repos", 
    "following": 0, 
    "login": "erasme"
}